impactmap/__init__.py
impactmap/client.py
impactmap/contacts.py
impactmap/impact_metrics.py
impactmap/projects.py
impactmap/tenants.py
impactmap-0.0.3.dist-info/licenses/LICENSE
impactmap-0.0.3.dist-info/METADATA
impactmap-0.0.3.dist-info/WHEEL
impactmap-0.0.3.dist-info/top_level.txt
impactmap-0.0.3.dist-info/RECORD
