Metadata-Version: 2.4
Name: impactmap
Version: 0.0.3
Summary: Official Python SDK for the ImpactMap API
Home-page: https://github.com/impactmap-io/impactmap-python
Author: ImpactMap.io
License: MIT License
Requires-Python: >=3.7
License-File: LICENSE
Requires-Dist: requests>=2.25.1
Dynamic: home-page
Dynamic: license-file
Dynamic: requires-python
